qurry/__init__.py
qurry/api.py
qurry/construct_initializer.py
qurry/postprocess.py
qurry/compiler/__init__.py
qurry/compiler/generate.py
qurry/compiler/parse.py
qurry/compiler/utils.py
qurry/constructs/CNU.py
qurry/constructs/CU.py
qurry/constructs/__init__.py
qurry/constructs/bernoulli.py
qurry/constructs/block.py
qurry/constructs/cascade.py
qurry/constructs/cascadeU.py
qurry/constructs/cond.py
qurry/constructs/datatype.py
qurry/constructs/defcircuit.py
qurry/constructs/define.py
qurry/constructs/do.py
qurry/constructs/gaussian.py
qurry/constructs/macro.py
qurry/constructs/map.py
qurry/constructs/multinomial.py
qurry/constructs/uniform.py
qurry/datatypes/__init__.py
qurry/datatypes/block.py
qurry/datatypes/datatype.py
qurry/datatypes/definitions.py
qurry/kernel/__init__.py
qurry/kernel/kernel.py
qurry/kernel/memory.py
qurry/kernel/topology.py
qurry/kernel/utils.py
qurry/library/__init__.py
qurry/library/controlled.py
qurry/library/curry.py
qurry/library/multinomial.py
qurry/visualization/__init__.py
qurry/visualization/histogram.py
qurry-0.0.3.data/scripts/compile
qurry-0.0.3.data/scripts/compile-qurry
qurry-0.0.3.data/scripts/quilarity
qurry-0.0.3.data/scripts/qurry-server
qurry-0.0.3.data/scripts/server
qurry-0.0.3.dist-info/LICENSE
qurry-0.0.3.dist-info/METADATA
qurry-0.0.3.dist-info/WHEEL
qurry-0.0.3.dist-info/top_level.txt
qurry-0.0.3.dist-info/RECORD
