Metadata-Version: 2.1
Name: qurry
Version: 0.0.3
Summary: A prototype quantum programming language
Home-page: https://github.com/LSaldyt/qurry
Author: Lucas Saldyt
Author-email: lucassaldyt@gmail.com
License: UNKNOWN
Platform: UNKNOWN
Classifier: Programming Language :: Python :: 3
Classifier: License :: OSI Approved :: MIT License
Classifier: Operating System :: OS Independent
